pytxrx/__init__.py
pytxrx/client.py
pytxrx/messages.py
pytxrx/server.py
pytxrx/txrx.py
pytxrx-0.1.0.dist-info/METADATA
pytxrx-0.1.0.dist-info/RECORD
pytxrx-0.1.0.dist-info/WHEEL
pytxrx-0.1.0.dist-info/top_level.txt
