Metadata-Version: 2.1
Name: pytxrx
Version: 0.1.0
Summary: Simple TCP string/byte tranferring
Home-page: http://github.com/tjkessler/pytxrx
Author: Travis Kessler
Author-email: travis.j.kessler@gmail.com
License: MIT
Platform: UNKNOWN
